{
  "match_id": "17ae1e32-5312-4d90-9a63-ec6624871f95.nakama-0",
  "map_id": "Lockdown",
  "player_count": 1,
  "human_count": 8,
  "bot_count": 0,
  "duration_ms": 1771045261,
  "events": [
    {
      "user_id": "b15bb032-6782-441a-9bd8-b42d446220cd",
      "player_type": "human",
      "event": "Loot",
      "x": -195.36268615722656,
      "z": 155.45591735839844,
      "y": 51.41896057128906,
      "ts": 1771045076,
      "pixel_x": 311,
      "pixel_y": 352
    },
    {
      "user_id": "b15bb032-6782-441a-9bd8-b42d446220cd",
      "player_type": "human",
      "event": "Position",
      "x": -190.990966796875,
      "z": 179.44000244140625,
      "y": 50.978416442871094,
      "ts": 1771045106,
      "pixel_x": 316,
      "pixel_y": 328
    },
    {
      "user_id": "b15bb032-6782-441a-9bd8-b42d446220cd",
      "player_type": "human",
      "event": "Loot",
      "x": -183.19129943847656,
      "z": 167.9353485107422,
      "y": 51.50808334350586,
      "ts": 1771045172,
      "pixel_x": 324,
      "pixel_y": 340
    },
    {
      "user_id": "b15bb032-6782-441a-9bd8-b42d446220cd",
      "player_type": "human",
      "event": "Loot",
      "x": -178.5528106689453,
      "z": 160.43521118164062,
      "y": 51.50808334350586,
      "ts": 1771045178,
      "pixel_x": 329,
      "pixel_y": 347
    },
    {
      "user_id": "b15bb032-6782-441a-9bd8-b42d446220cd",
      "player_type": "human",
      "event": "BotKill",
      "x": -194.83436584472656,
      "z": 169.70216369628906,
      "y": 51.52876663208008,
      "ts": 1771045200,
      "pixel_x": 312,
      "pixel_y": 338
    },
    {
      "user_id": "b15bb032-6782-441a-9bd8-b42d446220cd",
      "player_type": "human",
      "event": "Loot",
      "x": -193.9070587158203,
      "z": 166.63246154785156,
      "y": 51.51769256591797,
      "ts": 1771045205,
      "pixel_x": 313,
      "pixel_y": 341
    },
    {
      "user_id": "b15bb032-6782-441a-9bd8-b42d446220cd",
      "player_type": "human",
      "event": "BotKill",
      "x": -186.2751922607422,
      "z": 176.38182067871094,
      "y": 51.271026611328125,
      "ts": 1771045257,
      "pixel_x": 321,
      "pixel_y": 331
    },
    {
      "user_id": "b15bb032-6782-441a-9bd8-b42d446220cd",
      "player_type": "human",
      "event": "Loot",
      "x": -187.2543487548828,
      "z": 175.5631866455078,
      "y": 51.276771545410156,
      "ts": 1771045261,
      "pixel_x": 320,
      "pixel_y": 332
    }
  ]
}