{
  "match_id": "f28c42f8-9cbe-41d3-8506-73fdfa53aa47.nakama-0",
  "map_id": "AmbroseValley",
  "player_count": 7,
  "human_count": 36,
  "bot_count": 27,
  "duration_ms": 1770733262,
  "events": [
    {
      "user_id": "ff211ea2-fb53-42d3-a0b6-e781b8bad15c",
      "player_type": "human",
      "event": "Position",
      "x": -317.9846496582031,
      "z": 1.2531893253326416,
      "y": 125.52366638183594,
      "ts": 1770732589,
      "pixel_x": 59,
      "pixel_y": 484
    },
    {
      "user_id": "1439",
      "player_type": "bot",
      "event": "BotPosition",
      "x": 195.18121337890625,
      "z": -24.801328659057617,
      "y": 114.33638763427734,
      "ts": 1770732604,
      "pixel_x": 643,
      "pixel_y": 514
    },
    {
      "user_id": "1447",
      "player_type": "bot",
      "event": "BotPosition",
      "x": 175.5371856689453,
      "z": 136.74620056152344,
      "y": 103.591552734375,
      "ts": 1770732604,
      "pixel_x": 620,
      "pixel_y": 330
    },
    {
      "user_id": "ff211ea2-fb53-42d3-a0b6-e781b8bad15c",
      "player_type": "human",
      "event": "Loot",
      "x": -280.68011474609375,
      "z": 60.05656051635742,
      "y": 114.2284927368164,
      "ts": 1770732607,
      "pixel_x": 101,
      "pixel_y": 417
    },
    {
      "user_id": "ff211ea2-fb53-42d3-a0b6-e781b8bad15c",
      "player_type": "human",
      "event": "Loot",
      "x": -293.1435241699219,
      "z": 59.703956604003906,
      "y": 114.2284927368164,
      "ts": 1770732613,
      "pixel_x": 87,
      "pixel_y": 417
    },
    {
      "user_id": "ff211ea2-fb53-42d3-a0b6-e781b8bad15c",
      "player_type": "human",
      "event": "Loot",
      "x": -293.35400390625,
      "z": 62.45744323730469,
      "y": 114.2284927368164,
      "ts": 1770732614,
      "pixel_x": 87,
      "pixel_y": 414
    },
    {
      "user_id": "1443",
      "player_type": "bot",
      "event": "BotPosition",
      "x": -205.16847229003906,
      "z": -238.8857879638672,
      "y": 105.81526947021484,
      "ts": 1770732614,
      "pixel_x": 187,
      "pixel_y": 757
    },
    {
      "user_id": "1447",
      "player_type": "bot",
      "event": "BotPosition",
      "x": 161.94619750976562,
      "z": 103.46356201171875,
      "y": 113.24999237060547,
      "ts": 1770732614,
      "pixel_x": 605,
      "pixel_y": 368
    },
    {
      "user_id": "ff211ea2-fb53-42d3-a0b6-e781b8bad15c",
      "player_type": "human",
      "event": "Loot",
      "x": -276.93878173828125,
      "z": 70.43965911865234,
      "y": 114.2284927368164,
      "ts": 1770732619,
      "pixel_x": 105,
      "pixel_y": 405
    },
    {
      "user_id": "1455",
      "player_type": "bot",
      "event": "BotPosition",
      "x": -131.2766876220703,
      "z": 193.4276123046875,
      "y": 133.0445556640625,
      "ts": 1770732619,
      "pixel_x": 271,
      "pixel_y": 265
    },
    {
      "user_id": "ff211ea2-fb53-42d3-a0b6-e781b8bad15c",
      "player_type": "human",
      "event": "Loot",
      "x": -290.8319091796875,
      "z": 68.471923828125,
      "y": 114.2284927368164,
      "ts": 1770732622,
      "pixel_x": 90,
      "pixel_y": 407
    },
    {
      "user_id": "ff211ea2-fb53-42d3-a0b6-e781b8bad15c",
      "player_type": "human",
      "event": "Loot",
      "x": -286.4814758300781,
      "z": 74.86933898925781,
      "y": 114.0084228515625,
      "ts": 1770732627,
      "pixel_x": 95,
      "pixel_y": 400
    },
    {
      "user_id": "1443",
      "player_type": "bot",
      "event": "BotPosition",
      "x": -209.55117797851562,
      "z": -245.28912353515625,
      "y": 105.3797836303711,
      "ts": 1770732629,
      "pixel_x": 182,
      "pixel_y": 764
    },
    {
      "user_id": "ff211ea2-fb53-42d3-a0b6-e781b8bad15c",
      "player_type": "human",
      "event": "Position",
      "x": -213.35775756835938,
      "z": 98.8499526977539,
      "y": 111.78279113769531,
      "ts": 1770732644,
      "pixel_x": 178,
      "pixel_y": 373
    },
    {
      "user_id": "1459",
      "player_type": "bot",
      "event": "BotPosition",
      "x": -74.35260009765625,
      "z": -95.61272430419922,
      "y": 106.04138946533203,
      "ts": 1770732659,
      "pixel_x": 336,
      "pixel_y": 594
    },
    {
      "user_id": "1451",
      "player_type": "bot",
      "event": "BotPosition",
      "x": -184.14010620117188,
      "z": -322.0251159667969,
      "y": 124.02449798583984,
      "ts": 1770732664,
      "pixel_x": 211,
      "pixel_y": 852
    },
    {
      "user_id": "ff211ea2-fb53-42d3-a0b6-e781b8bad15c",
      "player_type": "human",
      "event": "Loot",
      "x": -124.12684631347656,
      "z": 93.96526336669922,
      "y": 102.68505096435547,
      "ts": 1770732667,
      "pixel_x": 279,
      "pixel_y": 378
    },
    {
      "user_id": "1451",
      "player_type": "bot",
      "event": "BotKill",
      "x": -189.09783935546875,
      "z": -324.7779541015625,
      "y": 123.44998931884766,
      "ts": 1770732680,
      "pixel_x": 205,
      "pixel_y": 855
    },
    {
      "user_id": "1451",
      "player_type": "bot",
      "event": "BotPosition",
      "x": -190.22802734375,
      "z": -323.85211181640625,
      "y": 123.44998931884766,
      "ts": 1770732684,
      "pixel_x": 204,
      "pixel_y": 854
    },
    {
      "user_id": "1447",
      "player_type": "bot",
      "event": "BotPosition",
      "x": 159.55035400390625,
      "z": 82.16294860839844,
      "y": 113.24999237060547,
      "ts": 1770732684,
      "pixel_x": 602,
      "pixel_y": 392
    },
    {
      "user_id": "ff211ea2-fb53-42d3-a0b6-e781b8bad15c",
      "player_type": "human",
      "event": "Loot",
      "x": -109.77784729003906,
      "z": 72.95392608642578,
      "y": 103.00311279296875,
      "ts": 1770732689,
      "pixel_x": 296,
      "pixel_y": 402
    },
    {
      "user_id": "ff211ea2-fb53-42d3-a0b6-e781b8bad15c",
      "player_type": "human",
      "event": "Loot",
      "x": -109.77784729003906,
      "z": 72.95392608642578,
      "y": 103.00311279296875,
      "ts": 1770732689,
      "pixel_x": 296,
      "pixel_y": 402
    },
    {
      "user_id": "ff211ea2-fb53-42d3-a0b6-e781b8bad15c",
      "player_type": "human",
      "event": "Loot",
      "x": -109.26680755615234,
      "z": 72.4581069946289,
      "y": 103.00311279296875,
      "ts": 1770732689,
      "pixel_x": 296,
      "pixel_y": 403
    },
    {
      "user_id": "1455",
      "player_type": "bot",
      "event": "BotPosition",
      "x": -108.55587768554688,
      "z": 78.85990905761719,
      "y": 103.04999542236328,
      "ts": 1770732709,
      "pixel_x": 297,
      "pixel_y": 396
    },
    {
      "user_id": "1447",
      "player_type": "bot",
      "event": "BotPosition",
      "x": 157.6031036376953,
      "z": 90.31582641601562,
      "y": 113.24999237060547,
      "ts": 1770732714,
      "pixel_x": 600,
      "pixel_y": 383
    },
    {
      "user_id": "ff211ea2-fb53-42d3-a0b6-e781b8bad15c",
      "player_type": "human",
      "event": "BotKill",
      "x": -116.61872100830078,
      "z": -37.99575424194336,
      "y": 104.94666290283203,
      "ts": 1770732719,
      "pixel_x": 288,
      "pixel_y": 529
    },
    {
      "user_id": "ff211ea2-fb53-42d3-a0b6-e781b8bad15c",
      "player_type": "human",
      "event": "Loot",
      "x": -111.59996795654297,
      "z": -41.10854721069336,
      "y": 104.94666290283203,
      "ts": 1770732721,
      "pixel_x": 294,
      "pixel_y": 532
    },
    {
      "user_id": "ff211ea2-fb53-42d3-a0b6-e781b8bad15c",
      "player_type": "human",
      "event": "Loot",
      "x": -111.94143676757812,
      "z": -41.12771224975586,
      "y": 104.94666290283203,
      "ts": 1770732722,
      "pixel_x": 293,
      "pixel_y": 532
    },
    {
      "user_id": "ff211ea2-fb53-42d3-a0b6-e781b8bad15c",
      "player_type": "human",
      "event": "Loot",
      "x": -99.6904296875,
      "z": -38.88718032836914,
      "y": 105.00367736816406,
      "ts": 1770732727,
      "pixel_x": 307,
      "pixel_y": 530
    },
    {
      "user_id": "1459",
      "player_type": "bot",
      "event": "BotPosition",
      "x": -93.06434631347656,
      "z": -71.98493194580078,
      "y": 102.06083679199219,
      "ts": 1770732734,
      "pixel_x": 315,
      "pixel_y": 567
    },
    {
      "user_id": "1459",
      "player_type": "bot",
      "event": "BotKilled",
      "x": -88.72161102294922,
      "z": -65.00762939453125,
      "y": 100.91355895996094,
      "ts": 1770732738,
      "pixel_x": 320,
      "pixel_y": 559
    },
    {
      "user_id": "ff211ea2-fb53-42d3-a0b6-e781b8bad15c",
      "player_type": "human",
      "event": "BotKill",
      "x": -89.57128143310547,
      "z": -52.77716827392578,
      "y": 103.3450927734375,
      "ts": 1770732738,
      "pixel_x": 319,
      "pixel_y": 545
    },
    {
      "user_id": "1451",
      "player_type": "bot",
      "event": "BotPosition",
      "x": -224.2722625732422,
      "z": -339.3976745605469,
      "y": 124.88824462890625,
      "ts": 1770732739,
      "pixel_x": 165,
      "pixel_y": 871
    },
    {
      "user_id": "ff211ea2-fb53-42d3-a0b6-e781b8bad15c",
      "player_type": "human",
      "event": "Position",
      "x": -90.57847595214844,
      "z": -52.83148193359375,
      "y": 103.65238189697266,
      "ts": 1770732739,
      "pixel_x": 317,
      "pixel_y": 545
    },
    {
      "user_id": "1443",
      "player_type": "bot",
      "event": "BotKill",
      "x": -78.20724487304688,
      "z": -95.05545806884766,
      "y": 107.02267456054688,
      "ts": 1770732747,
      "pixel_x": 331,
      "pixel_y": 593
    },
    {
      "user_id": "1443",
      "player_type": "bot",
      "event": "BotKilled",
      "x": -83.0993423461914,
      "z": -97.49787139892578,
      "y": 106.27983856201172,
      "ts": 1770732758,
      "pixel_x": 326,
      "pixel_y": 596
    },
    {
      "user_id": "ff211ea2-fb53-42d3-a0b6-e781b8bad15c",
      "player_type": "human",
      "event": "BotKill",
      "x": -98.89217376708984,
      "z": -93.09893798828125,
      "y": 106.12588500976562,
      "ts": 1770732758,
      "pixel_x": 308,
      "pixel_y": 591
    },
    {
      "user_id": "ff211ea2-fb53-42d3-a0b6-e781b8bad15c",
      "player_type": "human",
      "event": "Loot",
      "x": -83.44697570800781,
      "z": -97.75640869140625,
      "y": 106.12588500976562,
      "ts": 1770732763,
      "pixel_x": 326,
      "pixel_y": 597
    },
    {
      "user_id": "ff211ea2-fb53-42d3-a0b6-e781b8bad15c",
      "player_type": "human",
      "event": "Loot",
      "x": -83.44697570800781,
      "z": -97.75640869140625,
      "y": 106.12588500976562,
      "ts": 1770732763,
      "pixel_x": 326,
      "pixel_y": 597
    },
    {
      "user_id": "ff211ea2-fb53-42d3-a0b6-e781b8bad15c",
      "player_type": "human",
      "event": "Loot",
      "x": -89.0193862915039,
      "z": -65.28790283203125,
      "y": 100.79388427734375,
      "ts": 1770732773,
      "pixel_x": 319,
      "pixel_y": 560
    },
    {
      "user_id": "1439",
      "player_type": "bot",
      "event": "BotKilled",
      "x": 102.03460693359375,
      "z": -69.66625213623047,
      "y": 106.75874328613281,
      "ts": 1770732774,
      "pixel_x": 537,
      "pixel_y": 565
    },
    {
      "user_id": "ff211ea2-fb53-42d3-a0b6-e781b8bad15c",
      "player_type": "human",
      "event": "Loot",
      "x": -55.97249984741211,
      "z": -72.88272094726562,
      "y": 107.58140563964844,
      "ts": 1770732783,
      "pixel_x": 357,
      "pixel_y": 568
    },
    {
      "user_id": "1455",
      "player_type": "bot",
      "event": "BotPosition",
      "x": -140.3035125732422,
      "z": -75.09576416015625,
      "y": 104.99999237060547,
      "ts": 1770732785,
      "pixel_x": 261,
      "pixel_y": 571
    },
    {
      "user_id": "ff211ea2-fb53-42d3-a0b6-e781b8bad15c",
      "player_type": "human",
      "event": "Position",
      "x": -41.71363830566406,
      "z": -79.13201141357422,
      "y": 107.56271362304688,
      "ts": 1770732790,
      "pixel_x": 373,
      "pixel_y": 575
    },
    {
      "user_id": "1447",
      "player_type": "bot",
      "event": "BotKilled",
      "x": 134.9449920654297,
      "z": 68.25879669189453,
      "y": 113.24999237060547,
      "ts": 1770732798,
      "pixel_x": 574,
      "pixel_y": 408
    },
    {
      "user_id": "1451",
      "player_type": "bot",
      "event": "BotPosition",
      "x": -107.99128723144531,
      "z": -194.1243133544922,
      "y": 104.7064208984375,
      "ts": 1770732825,
      "pixel_x": 298,
      "pixel_y": 706
    },
    {
      "user_id": "1455",
      "player_type": "bot",
      "event": "BotKilled",
      "x": -2.3079652786254883,
      "z": -62.49528121948242,
      "y": 106.69840240478516,
      "ts": 1770732833,
      "pixel_x": 418,
      "pixel_y": 556
    },
    {
      "user_id": "ff211ea2-fb53-42d3-a0b6-e781b8bad15c",
      "player_type": "human",
      "event": "BotKill",
      "x": -1.648526668548584,
      "z": -83.00190734863281,
      "y": 107.23882293701172,
      "ts": 1770732833,
      "pixel_x": 419,
      "pixel_y": 580
    },
    {
      "user_id": "ff211ea2-fb53-42d3-a0b6-e781b8bad15c",
      "player_type": "human",
      "event": "Loot",
      "x": -2.258174180984497,
      "z": -63.15773010253906,
      "y": 106.68199920654297,
      "ts": 1770732842,
      "pixel_x": 418,
      "pixel_y": 557
    },
    {
      "user_id": "ff211ea2-fb53-42d3-a0b6-e781b8bad15c",
      "player_type": "human",
      "event": "Loot",
      "x": -2.258174180984497,
      "z": -63.15773010253906,
      "y": 106.68199920654297,
      "ts": 1770732842,
      "pixel_x": 418,
      "pixel_y": 557
    },
    {
      "user_id": "ff211ea2-fb53-42d3-a0b6-e781b8bad15c",
      "player_type": "human",
      "event": "BotKill",
      "x": 5.423023700714111,
      "z": -41.04253387451172,
      "y": 106.19361877441406,
      "ts": 1770732855,
      "pixel_x": 427,
      "pixel_y": 532
    },
    {
      "user_id": "ff211ea2-fb53-42d3-a0b6-e781b8bad15c",
      "player_type": "human",
      "event": "BotKill",
      "x": 5.548928260803223,
      "z": -41.02519989013672,
      "y": 106.20191955566406,
      "ts": 1770732857,
      "pixel_x": 427,
      "pixel_y": 532
    },
    {
      "user_id": "ff211ea2-fb53-42d3-a0b6-e781b8bad15c",
      "player_type": "human",
      "event": "Loot",
      "x": 6.074702739715576,
      "z": -24.927215576171875,
      "y": 106.3358383178711,
      "ts": 1770732863,
      "pixel_x": 427,
      "pixel_y": 514
    },
    {
      "user_id": "ff211ea2-fb53-42d3-a0b6-e781b8bad15c",
      "player_type": "human",
      "event": "Loot",
      "x": 5.419895648956299,
      "z": -24.435997009277344,
      "y": 106.47748565673828,
      "ts": 1770732863,
      "pixel_x": 427,
      "pixel_y": 513
    },
    {
      "user_id": "ff211ea2-fb53-42d3-a0b6-e781b8bad15c",
      "player_type": "human",
      "event": "Loot",
      "x": 8.562593460083008,
      "z": -14.087311744689941,
      "y": 106.54515075683594,
      "ts": 1770732866,
      "pixel_x": 430,
      "pixel_y": 501
    },
    {
      "user_id": "ff211ea2-fb53-42d3-a0b6-e781b8bad15c",
      "player_type": "human",
      "event": "Loot",
      "x": 8.562593460083008,
      "z": -14.087311744689941,
      "y": 106.54515075683594,
      "ts": 1770732867,
      "pixel_x": 430,
      "pixel_y": 501
    },
    {
      "user_id": "ff211ea2-fb53-42d3-a0b6-e781b8bad15c",
      "player_type": "human",
      "event": "BotKill",
      "x": 16.783594131469727,
      "z": -8.746597290039062,
      "y": 106.45922088623047,
      "ts": 1770732878,
      "pixel_x": 440,
      "pixel_y": 495
    },
    {
      "user_id": "ff211ea2-fb53-42d3-a0b6-e781b8bad15c",
      "player_type": "human",
      "event": "Position",
      "x": 20.625930786132812,
      "z": -13.101123809814453,
      "y": 106.59291076660156,
      "ts": 1770732880,
      "pixel_x": 444,
      "pixel_y": 500
    },
    {
      "user_id": "ff211ea2-fb53-42d3-a0b6-e781b8bad15c",
      "player_type": "human",
      "event": "Position",
      "x": 35.5208625793457,
      "z": -35.32058334350586,
      "y": 107.22176361083984,
      "ts": 1770732905,
      "pixel_x": 461,
      "pixel_y": 526
    },
    {
      "user_id": "1451",
      "player_type": "bot",
      "event": "BotPosition",
      "x": -85.44389343261719,
      "z": -156.67840576171875,
      "y": 100.34152221679688,
      "ts": 1770732925,
      "pixel_x": 323,
      "pixel_y": 664
    },
    {
      "user_id": "1451",
      "player_type": "bot",
      "event": "BotPosition",
      "x": -85.44390869140625,
      "z": -156.67840576171875,
      "y": 100.34152221679688,
      "ts": 1770733006,
      "pixel_x": 323,
      "pixel_y": 664
    },
    {
      "user_id": "1451",
      "player_type": "bot",
      "event": "BotPosition",
      "x": -31.729928970336914,
      "z": -186.0502471923828,
      "y": 121.97369384765625,
      "ts": 1770733242,
      "pixel_x": 384,
      "pixel_y": 697
    },
    {
      "user_id": "1451",
      "player_type": "bot",
      "event": "BotPosition",
      "x": -16.18368148803711,
      "z": -158.0702667236328,
      "y": 114.60677337646484,
      "ts": 1770733262,
      "pixel_x": 402,
      "pixel_y": 665
    }
  ]
}