{
  "match_id": "f06f75c0-a2ef-42ed-9fba-a836b201ec87.nakama-0",
  "map_id": "AmbroseValley",
  "player_count": 1,
  "human_count": 28,
  "bot_count": 0,
  "duration_ms": 1770733431,
  "events": [
    {
      "user_id": "d0a4f572-c8f3-4bcb-acf7-0af1ad19b635",
      "player_type": "human",
      "event": "Position",
      "x": 190.6512451171875,
      "z": 205.6177215576172,
      "y": 103.10136413574219,
      "ts": 1770733151,
      "pixel_x": 637,
      "pixel_y": 251
    },
    {
      "user_id": "d0a4f572-c8f3-4bcb-acf7-0af1ad19b635",
      "player_type": "human",
      "event": "Loot",
      "x": 190.6512451171875,
      "z": 205.6177215576172,
      "y": 103.10136413574219,
      "ts": 1770733152,
      "pixel_x": 637,
      "pixel_y": 251
    },
    {
      "user_id": "d0a4f572-c8f3-4bcb-acf7-0af1ad19b635",
      "player_type": "human",
      "event": "Loot",
      "x": 190.6512451171875,
      "z": 205.6177215576172,
      "y": 103.10136413574219,
      "ts": 1770733152,
      "pixel_x": 637,
      "pixel_y": 251
    },
    {
      "user_id": "d0a4f572-c8f3-4bcb-acf7-0af1ad19b635",
      "player_type": "human",
      "event": "Position",
      "x": 159.02606201171875,
      "z": 143.72642517089844,
      "y": 102.83831024169922,
      "ts": 1770733176,
      "pixel_x": 601,
      "pixel_y": 322
    },
    {
      "user_id": "d0a4f572-c8f3-4bcb-acf7-0af1ad19b635",
      "player_type": "human",
      "event": "Loot",
      "x": 159.3451690673828,
      "z": 142.78439331054688,
      "y": 102.83831024169922,
      "ts": 1770733180,
      "pixel_x": 602,
      "pixel_y": 323
    },
    {
      "user_id": "d0a4f572-c8f3-4bcb-acf7-0af1ad19b635",
      "player_type": "human",
      "event": "Loot",
      "x": 159.3451690673828,
      "z": 142.78439331054688,
      "y": 102.83831024169922,
      "ts": 1770733180,
      "pixel_x": 602,
      "pixel_y": 323
    },
    {
      "user_id": "d0a4f572-c8f3-4bcb-acf7-0af1ad19b635",
      "player_type": "human",
      "event": "Loot",
      "x": 159.3451690673828,
      "z": 142.78439331054688,
      "y": 102.83831024169922,
      "ts": 1770733180,
      "pixel_x": 602,
      "pixel_y": 323
    },
    {
      "user_id": "d0a4f572-c8f3-4bcb-acf7-0af1ad19b635",
      "player_type": "human",
      "event": "BotKill",
      "x": 147.26446533203125,
      "z": 93.79338073730469,
      "y": 112.44457244873047,
      "ts": 1770733196,
      "pixel_x": 588,
      "pixel_y": 379
    },
    {
      "user_id": "d0a4f572-c8f3-4bcb-acf7-0af1ad19b635",
      "player_type": "human",
      "event": "Position",
      "x": 147.26446533203125,
      "z": 93.79338073730469,
      "y": 112.44457244873047,
      "ts": 1770733196,
      "pixel_x": 588,
      "pixel_y": 379
    },
    {
      "user_id": "d0a4f572-c8f3-4bcb-acf7-0af1ad19b635",
      "player_type": "human",
      "event": "Loot",
      "x": 148.93511962890625,
      "z": 77.83330535888672,
      "y": 113.20938873291016,
      "ts": 1770733203,
      "pixel_x": 590,
      "pixel_y": 397
    },
    {
      "user_id": "d0a4f572-c8f3-4bcb-acf7-0af1ad19b635",
      "player_type": "human",
      "event": "Loot",
      "x": 149.6336212158203,
      "z": 74.68660736083984,
      "y": 113.20938873291016,
      "ts": 1770733206,
      "pixel_x": 591,
      "pixel_y": 400
    },
    {
      "user_id": "d0a4f572-c8f3-4bcb-acf7-0af1ad19b635",
      "player_type": "human",
      "event": "Position",
      "x": 149.6336212158203,
      "z": 74.68660736083984,
      "y": 113.20938873291016,
      "ts": 1770733206,
      "pixel_x": 591,
      "pixel_y": 400
    },
    {
      "user_id": "d0a4f572-c8f3-4bcb-acf7-0af1ad19b635",
      "player_type": "human",
      "event": "Loot",
      "x": 148.83544921875,
      "z": 72.26433563232422,
      "y": 113.20938873291016,
      "ts": 1770733208,
      "pixel_x": 590,
      "pixel_y": 403
    },
    {
      "user_id": "d0a4f572-c8f3-4bcb-acf7-0af1ad19b635",
      "player_type": "human",
      "event": "Loot",
      "x": 148.83544921875,
      "z": 72.26433563232422,
      "y": 113.20938873291016,
      "ts": 1770733208,
      "pixel_x": 590,
      "pixel_y": 403
    },
    {
      "user_id": "d0a4f572-c8f3-4bcb-acf7-0af1ad19b635",
      "player_type": "human",
      "event": "Position",
      "x": 145.9404754638672,
      "z": 70.33978271484375,
      "y": 113.20938873291016,
      "ts": 1770733241,
      "pixel_x": 587,
      "pixel_y": 405
    },
    {
      "user_id": "d0a4f572-c8f3-4bcb-acf7-0af1ad19b635",
      "player_type": "human",
      "event": "Loot",
      "x": 140.6729736328125,
      "z": 61.37739181518555,
      "y": 113.21273040771484,
      "ts": 1770733251,
      "pixel_x": 581,
      "pixel_y": 415
    },
    {
      "user_id": "d0a4f572-c8f3-4bcb-acf7-0af1ad19b635",
      "player_type": "human",
      "event": "Loot",
      "x": 179.14588928222656,
      "z": 75.82389831542969,
      "y": 113.31831359863281,
      "ts": 1770733272,
      "pixel_x": 624,
      "pixel_y": 399
    },
    {
      "user_id": "d0a4f572-c8f3-4bcb-acf7-0af1ad19b635",
      "player_type": "human",
      "event": "Loot",
      "x": 170.70632934570312,
      "z": 78.10084533691406,
      "y": 113.31831359863281,
      "ts": 1770733275,
      "pixel_x": 615,
      "pixel_y": 396
    },
    {
      "user_id": "d0a4f572-c8f3-4bcb-acf7-0af1ad19b635",
      "player_type": "human",
      "event": "Loot",
      "x": 174.15036010742188,
      "z": 72.45984649658203,
      "y": 113.31831359863281,
      "ts": 1770733280,
      "pixel_x": 619,
      "pixel_y": 403
    },
    {
      "user_id": "d0a4f572-c8f3-4bcb-acf7-0af1ad19b635",
      "player_type": "human",
      "event": "Position",
      "x": 174.43212890625,
      "z": 70.08346557617188,
      "y": 113.31831359863281,
      "ts": 1770733282,
      "pixel_x": 619,
      "pixel_y": 406
    },
    {
      "user_id": "d0a4f572-c8f3-4bcb-acf7-0af1ad19b635",
      "player_type": "human",
      "event": "Loot",
      "x": 175.81434631347656,
      "z": 69.11917877197266,
      "y": 113.31831359863281,
      "ts": 1770733284,
      "pixel_x": 621,
      "pixel_y": 407
    },
    {
      "user_id": "d0a4f572-c8f3-4bcb-acf7-0af1ad19b635",
      "player_type": "human",
      "event": "Loot",
      "x": 189.7234649658203,
      "z": 88.71617126464844,
      "y": 113.22946166992188,
      "ts": 1770733302,
      "pixel_x": 636,
      "pixel_y": 384
    },
    {
      "user_id": "d0a4f572-c8f3-4bcb-acf7-0af1ad19b635",
      "player_type": "human",
      "event": "Loot",
      "x": 165.5479736328125,
      "z": -69.23365020751953,
      "y": 106.81998443603516,
      "ts": 1770733344,
      "pixel_x": 609,
      "pixel_y": 564
    },
    {
      "user_id": "d0a4f572-c8f3-4bcb-acf7-0af1ad19b635",
      "player_type": "human",
      "event": "Loot",
      "x": 160.94058227539062,
      "z": -62.320892333984375,
      "y": 106.81998443603516,
      "ts": 1770733349,
      "pixel_x": 604,
      "pixel_y": 556
    },
    {
      "user_id": "d0a4f572-c8f3-4bcb-acf7-0af1ad19b635",
      "player_type": "human",
      "event": "Loot",
      "x": 161.42178344726562,
      "z": -62.533851623535156,
      "y": 106.81998443603516,
      "ts": 1770733367,
      "pixel_x": 604,
      "pixel_y": 556
    },
    {
      "user_id": "d0a4f572-c8f3-4bcb-acf7-0af1ad19b635",
      "player_type": "human",
      "event": "Loot",
      "x": 162.89776611328125,
      "z": -69.85037994384766,
      "y": 106.81998443603516,
      "ts": 1770733386,
      "pixel_x": 606,
      "pixel_y": 565
    },
    {
      "user_id": "d0a4f572-c8f3-4bcb-acf7-0af1ad19b635",
      "player_type": "human",
      "event": "Loot",
      "x": 151.8991241455078,
      "z": -77.32958984375,
      "y": 106.81998443603516,
      "ts": 1770733414,
      "pixel_x": 593,
      "pixel_y": 573
    },
    {
      "user_id": "d0a4f572-c8f3-4bcb-acf7-0af1ad19b635",
      "player_type": "human",
      "event": "Loot",
      "x": 147.29733276367188,
      "z": -78.83358001708984,
      "y": 106.81998443603516,
      "ts": 1770733431,
      "pixel_x": 588,
      "pixel_y": 575
    }
  ]
}